pytorch_multilabel_balanced_sampler-0.1.3.dist-info/METADATA
pytorch_multilabel_balanced_sampler-0.1.3.dist-info/WHEEL
pytorch_multilabel_balanced_sampler-0.1.3.dist-info/licenses/LICENSE
pytorch_multilabel_balanced_sampler/__init__.py
pytorch_multilabel_balanced_sampler/samplers.py
pytorch_multilabel_balanced_sampler/validation.py
pytorch_multilabel_balanced_sampler-0.1.3.dist-info/RECORD
