Metadata-Version: 2.1
Name: pytorch-multilabel-balanced-sampler
Version: 0.1.3
Summary: PyTorch samplers that output roughly balanced batches with support for multilabel datasets.
Author-Email: Issa Memari <issa.memari@gmail.com>
License: MIT
Requires-Python: >=3.8
Requires-Dist: torch
